memorymarker/__init__.py
memorymarker/__main__.py
memorymarker/py.typed
memorymarker/cli/document_selector.py
memorymarker/document_providers/ContextualizedHighlight.py
memorymarker/document_providers/Document.py
memorymarker/document_providers/__init__.py
memorymarker/document_providers/base.py
memorymarker/document_providers/hypothesis.py
memorymarker/document_providers/omnivore.py
memorymarker/document_providers/test_omnivore.py
memorymarker/document_providers/hydrator/__init__.py
memorymarker/document_providers/hydrator/main.py
memorymarker/document_providers/hydrator/test_hydrator.py
memorymarker/persist_questions/__init__.py
memorymarker/persist_questions/markdown.py
memorymarker/persist_questions/test_markdown.py
memorymarker/persist_questions/__snapshots__/test_markdown.ambr
memorymarker/prompts/martin_prompt.txt
memorymarker/question_generator/__init__.py
memorymarker/question_generator/prompts_from_string.py
memorymarker/question_generator/question_generator.py
memorymarker/question_generator/test_highlights_to_questions.py
memorymarker-0.4.1.dist-info/LICENSE
memorymarker-0.4.1.dist-info/METADATA
memorymarker-0.4.1.dist-info/WHEEL
memorymarker-0.4.1.dist-info/entry_points.txt
memorymarker-0.4.1.dist-info/top_level.txt
memorymarker-0.4.1.dist-info/RECORD
