Metadata-Version: 2.1
Name: memorymarker
Version: 0.4.1
Summary: memorymarker
Author-email: Martin Bernstorff <martinbernstorff@gmail.com>
License: MIT License
Project-URL: homepage, https://github.com/MartinBernstorff/memorymarker
Project-URL: repository, https://github.com/MartinBernstorff/memorymarker
Project-URL: documentation, https://MartinBernstorff.github.io/memorymarker/
Classifier: Programming Language :: Python :: 3.12
Requires-Python: >=3.12
License-File: LICENSE
Requires-Dist: beautifulsoup4 >=4.12.3
Requires-Dist: iterpy >=1.6.0
Requires-Dist: joblib >=1.3.2
Requires-Dist: langchain ==0.0.300
Requires-Dist: omnivoreql >=0.2.1
Requires-Dist: openai ==0.28.0
Requires-Dist: pydantic >=2.6.2
Requires-Dist: python-dotenv >=1.0.1
Requires-Dist: pytz >=2024.1
Requires-Dist: typer >=0.9.0
Requires-Dist: questionary >=2.0.1
